bts/__cli__.py
bts/__init__.py
bts/_version.py
bts/conf/about/__init__.yaml
bts/py.typed
jejubts-0.1.1.dist-info/LICENSE
jejubts-0.1.1.dist-info/METADATA
jejubts-0.1.1.dist-info/WHEEL
jejubts-0.1.1.dist-info/entry_points.txt
jejubts-0.1.1.dist-info/RECORD
