Metadata-Version: 2.1
Name: jejubts
Version: 0.1.1
Summary: bts project
Home-page: https://202021013.github.io/bts
License: MIT
Author: Jiyeon Kim
Author-email: 202021013@chu.ac.kr
Requires-Python: >=3.8.1,<3.12
Classifier: License :: OSI Approved :: MIT License
Classifier: Programming Language :: Python :: 3
Classifier: Programming Language :: Python :: 3.9
Classifier: Programming Language :: Python :: 3.10
Classifier: Programming Language :: Python :: 3.11
Project-URL: Repository, https://github.com/202021013/bts
